khoshnevis/URL.py
khoshnevis/__init__.py
khoshnevis/dictionary.py
khoshnevis/emoji.py
khoshnevis/ending.py
khoshnevis/normalizer.py
khoshnevis/space.py
khoshnevis-0.1.5.dist-info/METADATA
khoshnevis-0.1.5.dist-info/WHEEL
khoshnevis-0.1.5.dist-info/top_level.txt
khoshnevis-0.1.5.dist-info/RECORD
