Metadata-Version: 2.1
Name: khoshnevis
Version: 0.1.5
Summary: Khodnevis Normalizer
Home-page: https://www.khodnevisai.com/
Author: khodnevisAI
Author-email: khodnevis.group@gmail.com
License: UNKNOWN
Keywords: python,persian,normalizer,text
Platform: UNKNOWN
Classifier: Topic :: Text Processing
Classifier: Natural Language :: Persian
Classifier: Programming Language :: Python :: 3
Requires-Dist: parsivar (==0.2.3)
Requires-Dist: demoji (==1.1.0)
